spotriver/data/UnivariateData.csv
spotriver/data/__init__.py
spotriver/data/airline-passengers.csv
spotriver/data/airline_passengers.py
spotriver/data/base.py
spotriver/data/bike_sharing.py
spotriver/data/csvdataset.py
spotriver/data/generic.py
spotriver/data/opm.py
spotriver/data/selector.py
spotriver/data/synth/__init__.py
spotriver/data/synth/sea.py
spotriver/drift/drift_generator.py
spotriver/evaluation/eval_bml.py
spotriver/evaluation/eval_nowcast.py
spotriver/evaluation/eval_oml.py
spotriver/fun/hyperriver.py
spotriver/fun/hyperriver_old.py
spotriver/hyperdict/river_hyper_dict.json
spotriver/hyperdict/river_hyper_dict.py
spotriver/plot/stats.py
spotriver/preprocess/impute.py
spotriver/utils/data_conversion.py
spotriver/utils/features.py
spotriver-0.4.4.dist-info/LICENSE
spotriver-0.4.4.dist-info/METADATA
spotriver-0.4.4.dist-info/WHEEL
spotriver-0.4.4.dist-info/top_level.txt
spotriver-0.4.4.dist-info/RECORD
