Metadata-Version: 2.1
Name: spotriver
Version: 0.4.4
Summary: spotriver - Sequential Parameter Optimization Interface to River
Author-email: "T. Bartz-Beielstein" <tbb@bartzundbartz.de>
Project-URL: Homepage, https://www.spotseven.de
Classifier: Programming Language :: Python :: 3.10
Classifier: Programming Language :: Python :: 3.11
Classifier: Programming Language :: Python :: 3.12
Classifier: Operating System :: OS Independent
Requires-Python: >=3.10
License-File: LICENSE
Requires-Dist: lightning >=2.0.0rc0
Requires-Dist: matplotlib
Requires-Dist: numpy
Requires-Dist: nbformat
Requires-Dist: mkdocstrings-python
Requires-Dist: pandas
Requires-Dist: plotly
Requires-Dist: pytest
Requires-Dist: pytorch-lightning >=1.4
Requires-Dist: river >=0.21.2
Requires-Dist: scikit-learn
Requires-Dist: scipy
Requires-Dist: spotpython >=0.15.7
Requires-Dist: seaborn
Requires-Dist: tabulate
Requires-Dist: tensorboard
Requires-Dist: torch
Requires-Dist: torch-tb-profiler
Requires-Dist: torchmetrics
Requires-Dist: torchvision
